Workbook

Sheet Summary
A1: NUCLEUS SATELLITE COMMUNICATIONS (MADRAS) PRIVATE LIMITED
A2: GSTIN: 37AAACN9960D2ZA (Andhra)
A4: Form GSTR-1 Summary for the month of Jan'26
A5: Particulars | B5: Taxable value | C5: Integrated tax | D5: CGST | E5: SGST | F5: Total Tax Payable
A6: Outward Taxable supplies | B6: 0 | C6: =+GSTR1!I8 -> 0 | D6: 0 | E6: 0 | F6: =+C6+D6+E6 -> 0
A7: Less: Inward Taxable supplies | B7: 0 | C7: =ROUND(B7*18/100,0) -> 0 | D7: =ROUND(B7*9/100,0) -> 0 | E7: =ROUND(B7*9/100,0) -> 0 | F7: =SUM(D7:E7) -> 0
A8: Payable Amount | C8: =SUM(C6:C7) -> 0 | D8: =+D6-D7 -> 0 | E8: =+E6-E7 -> 0 | F8: =+F6-F7 -> 0
A10: Form GSTR-3B Summary for the month of Jan'26
A11: Particulars | B11: Taxable value | C11: Integrated tax | D11: CGST | E11: SGST | F11: Total Tax Payable
A12: Reverse charge | B12: =+GSTR3B!I11 -> 62300 | C12: =+GSTR3B!J11 -> 0 | D12: =GSTR3B!K11 -> 5607 | E12: =GSTR3B!L11 -> 5607 | F12: =+C12+D12+E12 -> 11214
A13: Payable Amount | C13: =SUM(C12) -> 0 | D13: =SUM(D12) -> 5607 | E13: =SUM(E12) -> 5607 | F13: =SUM(F12) -> 11214
A15: Total | C15: =+C8+C13 -> 0 | D15: =+D8+D13 -> 5607 | E15: =+E8+E13 -> 5607 | F15: =+F8+F13 -> 11214
A17: Tax paid Through ITC
A18: Particulars | B18: Taxable value | C18: IGST Credit | D18: CGST Credit | E18: SGST Credit | F18: Total
A19: Opening balance -Cash Ledger | B19: 0 | C19: 0 | D19: 0 | E19: 0 | F19: =+C19+D19+E19 -> 0
A20: Opening balance -Credit Ledger | C20: 807009 | D20: 139430 | E20: 139430 | F20: =SUM(C20:E20) -> 1085869 | I20: 3889439.2 | J20: 700930
A21: Input credit RCM - Jan'26 | B21: =+GSTR3B!I11 -> 62300 | C21: =+C13 -> 0 | D21: =+D13 -> 5607 | E21: =+E13 -> 5607 | F21: =SUM(C21:E21) -> 11214
A22: Input credit - Jan'26 | B22: =+Sheet1!J27 -> 0 | C22: =+Sheet1!K27 -> 0 | D22: =+Sheet1!L27 -> 0 | E22: =+Sheet1!M27 -> 0 | F22: =SUM(C22:E22) -> 0
A23: Reversal | F23: =+#REF! -> #REF!
A24: Total | B24: =SUM(B20:B22) -> 62300 | C24: =SUM(C20:C22)-C23 -> 807009 | D24: =SUM(D20:D22)-D23 -> 145037 | E24: =SUM(E20:E22)-E23 -> 145037 | F24: =SUM(F20:F22)-F23 -> #REF!
A26: Payable amount for Jan'26 | B26: =+GSTR3B!I11 -> 62300 | C26: =+C15 -> 0 | D26: =+D15 -> 5607 | E26: =+E15 -> 5607 | F26: =+F15 -> 11214
A28: Cash Ledger balance | C28: 0 | D28: 0 | E28: 0 | F28: =+C28+D28+E28 -> 0
A29: Credit Ledger balance | B29: =+B24 -> 62300 | C29: =+C24 -> 807009 | D29: =+D24 -> 145037 | E29: =+E24 -> 145037 | F29: =+C29+D29+E29 -> 1097083 | J29: =+D30-J30 -> -555893 | K29: =+E30-K30 -> -555893
A30: Total | B30: =SUM(B28:B29) -> 62300 | C30: =SUM(C28:C29) -> 807009 | D30: =SUM(D28:D29) -> 145037 | E30: =SUM(E28:E29) -> 145037 | F30: =SUM(F28:F29) -> 1097083 | I30: 3889439.2 | J30: 700930 | K30: 700930
I31: 54000 | J31: =SUM(J29:J30) -> 145037 | K31: =SUM(K29:K30) -> 145037

Sheet GSTR1
A1: =+Summary!A1 -> NUCLEUS SATELLITE COMMUNICATIONS (MADRAS) PRIVATE LIMITED
A2: GSTR Details for the month of Jan'26
A3: S.No. | B3: Name of the recipient | C3: GSTIN/ UIN | D3: Invoice details | G3: Rate | H3: Taxable value | I3: Amount | M3: Place of supply (Name of State/ UT) | N3: Code
D4: No. | E4: Date | F4: Value | I4: Integrated tax | J4: Central Tax | K4: State/UT Tax | L4: Cess | N4: Code
C5: 1 | D5: 2 | E5: 3 | F5: 4 | G5: 5 | H5: 6 | I5: 7 | J5: 8 | K5: 9 | L5: 10 | M5: 11
B8: Total | F8: =SUM(F6:F7) -> 0 | G8: =SUM(G6:G7) -> 0 | H8: =SUM(H6:H7) -> 0 | I8: =SUM(I6:I7) -> 0 | J8: =SUM(J6:J7) -> 0 | K8: =SUM(K6:K7) -> 0 | L8: =SUM(L6:L6) -> 0
H20: 8002.5
D21: =4960+3720 -> 8680 | E21: =+D21*8084 -> 70169120
E22: =+E21*12% -> 8420294.4
E23: =SUM(E21:E22) -> 78589414
D25: =620*14 -> 8680 | E25: 8002.5 | F25: =+D25*E25 -> 69461700
D26: =+D21-D25 -> 0 | E26: =+E25*1% -> 80.025 | F26: =+F25*12% -> 8335404
E27: =SUM(E25:E26) -> 8082.525 | F27: =SUM(F25:F26) -> 77797104

Sheet GSTR3B
A1: =+Summary!A1 -> NUCLEUS SATELLITE COMMUNICATIONS (MADRAS) PRIVATE LIMITED
A2: GSTR Detaisl for the month of Jan'26
A3: S.No. | B3: Name of the Vendor | C3: Account head | D3: GSTIN/ UIN | E3: Invoice details | H3: Rate | I3: Taxable value | J3: Amount | N3: Place of supply (Name of State/ UT) | O3: Code
E4: No. | F4: Date | G4: Value | J4: Integrated tax | K4: Central Tax | L4: State/UT Tax | M4: Cess | O4: Code
D5: 1 | E5: 2 | F5: 3 | G5: 4 | H5: 5 | I5: 6 | J5: 7 | K5: 8 | L5: 9 | M5: 10 | N5: 11
A6: 1 | B6: SD Projects | D6: 37DLZPP3296N1ZP | E6: 46 | F6: 31.12.2025 | G6: 62300 | H6: 0.18 | I6: 62300 | J6: 0 | K6: =I6*9/100 -> 5607 | L6: =I6*9/100 -> 5607 | M6: 0
B11: Total | G11: =SUM(G6:G10) -> 62300 | I11: =SUM(I6:I10) -> 62300 | J11: =SUM(J6:J10) -> 0 | K11: =SUM(K6:K10) -> 5607 | L11: =SUM(L6:L10) -> 5607 | M11: =SUM(M6:M10) -> 0
I14: Net Payable Amount | L14: =+J11+K11+L11 -> 11214

Sheet Sheet1
A1: Goods and Services Tax - GSTR-2B
A4: Taxable inward supplies received from registered persons
A5: GSTIN of supplier | B5: Trade/Legal name | C5: Invoice Details | H5: Place of supply | I5: Supply Attract Reverse Charge | J5: Taxable Value (₹) | K5: Tax Amount | O5: GSTR-1/1A/IFF/GSTR-5 Period | P5: GSTR-1/1A/IFF/GSTR-5 Filing Date | Q5: ITC Availability | R5: Reason | S5: Applicable % of Tax Rate | T5: Source | U5: IRN | V5: IRN Date
C6: Invoice number | D6: Invoice type | E6: Invoice Date | F6: Invoice Value(₹) | G6: Action | K6: Integrated Tax(₹) | L6: Central Tax(₹) | M6: State/UT Tax(₹) | N6: Cess(₹)
A7: 36AAACH2702H1Z1 | B7: HDFC BANK LMITED | C7: CDT2601338667928 | D7: Regular | E7: 31/01/2026 | F7: 88.5 | G7: Accepted | H7: Andhra Pradesh | I7: No | J7: 75 | K7: 13.5 | L7: 0 | M7: 0 | N7: 0 | O7: Jan'26 | P7: 10/02/2026 | Q7: Yes | S7: 100%
A8: 37DLZPP3296N1ZP | B8: S D PROJECTS | C8: 53 | D8: Regular | E8: 31/01/2026 | F8: 109065 | G8: Pending | H8: Andhra Pradesh | I8: Yes | J8: 92428 | K8: 0 | L8: 8318.52 | M8: 8318.52 | N8: 0 | O8: Jan'26 | P8: 07/02/2026 | Q8: Yes | S8: 100%
I9: Total | J9: =SUM(J7:J8) -> 92503 | K9: =SUM(K7:K8) -> 13.5 | L9: =SUM(L7:L8) -> 8318.52 | M9: =SUM(M7:M8) -> 8318.52
I13: ITC Reversed | J13: 0 | K13: 0 | L13: 0 | M13: 0 | N13: 0
I14: ITC taken for Jan'26 | J14: 75 | K14: 13.5 | L14: 0 | M14: 0 | N14: 0
I15: GSTR 3B | J15: =GSTR3B!I6 -> 62300 | K15: =GSTR3B!J6 -> 0 | L15: =GSTR3B!K6 -> 5607 | M15: =GSTR3B!L6 -> 5607 | N15: =GSTR3B!M6 -> 0
I16: ITC available | J16: =+J14+J15 -> 62375 | K16: =+K14+K15 -> 13.5 | L16: =+L14+L15 -> 5607 | M16: =+M14+M15 -> 5607 | N16: =+N14+N15 -> 0
